{
    "7DT14": {
        "g": {
            "update_time": "2000-01-01T00:00:00.000",
            "succeeded": false,
            "focusval": 10000
        },
        "r": {
            "update_time": "2000-01-01T00:00:00.000",
            "succeeded": false,
            "focusval": 10000
        },
        "i": {
            "update_time": "2000-01-01T00:00:00.000",
            "succeeded": false,
            "focusval": 10000
        },
        "m600": {
            "update_time": "2024-11-23T06:22:56.696",
            "succeeded": true,
            "focusval": 9311.8
        },
        "m625": {
            "update_time": "2024-11-23T06:30:27.125",
            "succeeded": true,
            "focusval": 9464.9
        },
        "m500": {
            "update_time": "2000-01-01T00:00:00.000",
            "succeeded": false,
            "focusval": 10000
        },
        "m775": {
            "update_time": "2000-01-01T00:00:00.000",
            "succeeded": false,
            "focusval": 10000
        },
        "Slot8": {
            "update_time": "2000-01-01T00:00:00.000",
            "succeeded": false,
            "focusval": 10000
        },
        "Slot9": {
            "update_time": "2000-01-01T00:00:00.000",
            "succeeded": false,
            "focusval": 10000
        }
    }
}