{
    "7DT12": {
        "g": {
            "update_time": "2000-01-01T00:00:00.000",
            "succeeded": false,
            "focusval": 10000,
            "focuserr": 999
        },
        "r": {
            "update_time": "2000-01-01T00:00:00.000",
            "succeeded": false,
            "focusval": 10000,
            "focuserr": 999
        },
        "i": {
            "update_time": "2000-01-01T00:00:00.000",
            "succeeded": false,
            "focusval": 10000,
            "focuserr": 999
        },
        "m850": {
            "update_time": "2025-07-03T10:11:28.914",
            "succeeded": true,
            "focusval": 4721.7,
            "focuserr": 20.61
        },
        "m875": {
            "update_time": "2025-07-03T10:18:25.622",
            "succeeded": true,
            "focusval": 4708.1,
            "focuserr": 19.61
        },
        "Slot6": {
            "update_time": "2000-01-01T00:00:00.000",
            "succeeded": false,
            "focusval": 10000,
            "focuserr": 999
        },
        "Slot7": {
            "update_time": "2000-01-01T00:00:00.000",
            "succeeded": false,
            "focusval": 10000,
            "focuserr": 999
        },
        "Slot8": {
            "update_time": "2000-01-01T00:00:00.000",
            "succeeded": false,
            "focusval": 10000,
            "focuserr": 999
        },
        "Slot9": {
            "update_time": "2000-01-01T00:00:00.000",
            "succeeded": false,
            "focusval": 10000,
            "focuserr": 999
        }
    }
}